zav/__init__.py
zav/agents_sdk/__init__.py
zav/agents_sdk/_hack.py
zav/agents_sdk/bootstrap.py
zav/agents_sdk/exception_handlers.py
zav/agents_sdk/mem_utils.py
zav/agents_sdk/security.py
zav/agents_sdk/setup_app.py
zav/agents_sdk/version.py
zav/agents_sdk/adapters/__init__.py
zav/agents_sdk/adapters/async_wrapper.py
zav/agents_sdk/adapters/local_agent_registries_factory.py
zav/agents_sdk/adapters/agent_setup_retrievers/__init__.py
zav/agents_sdk/adapters/agent_setup_retrievers/from_file.py
zav/agents_sdk/adapters/agent_setup_retrievers/from_local.py
zav/agents_sdk/adapters/event_publishers/__init__.py
zav/agents_sdk/adapters/event_publishers/event_publisher.py
zav/agents_sdk/adapters/llm_models/__init__.py
zav/agents_sdk/adapters/llm_models/langchain_chat_anthropic.py
zav/agents_sdk/adapters/llm_models/langchain_chat_bedrock.py
zav/agents_sdk/adapters/llm_models/langchain_chat_openai.py
zav/agents_sdk/adapters/llm_models/zav_chat_completion_client.py
zav/agents_sdk/adapters/mcp/__init__.py
zav/agents_sdk/adapters/mcp/strict_schema.py
zav/agents_sdk/adapters/mcp/tools_provider.py
zav/agents_sdk/adapters/retrievers/__init__.py
zav/agents_sdk/adapters/retrievers/zav_langchain_retriever.py
zav/agents_sdk/adapters/retrievers/zav_retriever.py
zav/agents_sdk/behavior/__init__.py
zav/agents_sdk/behavior/assertions.py
zav/agents_sdk/behavior/harness.py
zav/agents_sdk/behavior/models.py
zav/agents_sdk/cli/__init__.py
zav/agents_sdk/cli/load_chat_agent_factory.py
zav/agents_sdk/cli/local_app.py
zav/agents_sdk/cli/main.py
zav/agents_sdk/cli/models.py
zav/agents_sdk/cli/ui_app.py
zav/agents_sdk/cli/utils.py
zav/agents_sdk/cli/pages/__init__.py
zav/agents_sdk/cli/pages/ui_collect.py
zav/agents_sdk/cli/pages/ui_eval.py
zav/agents_sdk/controllers/__init__.py
zav/agents_sdk/controllers/v1/__init__.py
zav/agents_sdk/controllers/v1/common.py
zav/agents_sdk/controllers/v1/chats/__init__.py
zav/agents_sdk/controllers/v1/chats/controllers.py
zav/agents_sdk/controllers/v1/chats/types.py
zetaalpha_rag_agents-0.0.11.dist-info/METADATA
zetaalpha_rag_agents-0.0.11.dist-info/WHEEL
zetaalpha_rag_agents-0.0.11.dist-info/entry_points.txt
zetaalpha_rag_agents-0.0.11.dist-info/top_level.txt
zetaalpha_rag_agents-0.0.11.dist-info/RECORD
