Metadata-Version: 2.4
Name: zetaalpha.rag-agents
Version: 0.0.11
Summary: The Agents SDK is designed to provide a flexible, scalable, and efficient framework for building, testing, and deploying LLM agents.
Author-email: Zeta Alpha Vector <support@zeta-alpha.com>
Project-URL: Homepage, https://github.com/zetaalphavector/platform
Project-URL: Repository, https://github.com/zetaalphavector/platform
Project-URL: Issues, https://github.com/zetaalphavector/platform/issues
Classifier: Topic :: Utilities
Classifier: Intended Audience :: Developers
Classifier: Intended Audience :: Information Technology
Classifier: Operating System :: OS Independent
Classifier: Programming Language :: Python :: 3.8
Requires-Python: >=3.12
Requires-Dist: aiofiles==24.1.0
Requires-Dist: aiohappyeyeballs==2.6.1
Requires-Dist: aiohttp==3.12.15
Requires-Dist: aiosignal==1.4.0
Requires-Dist: altair==5.5.0
Requires-Dist: annotated-types==0.7.0
Requires-Dist: anyio==4.10.0
Requires-Dist: attrs==25.3.0
Requires-Dist: azure-core==1.35.1
Requires-Dist: azure-identity==1.25.0
Requires-Dist: azure-storage-blob==12.26.0
Requires-Dist: blinker==1.9.0
Requires-Dist: boto3==1.40.35
Requires-Dist: botocore==1.40.35
Requires-Dist: cachetools==6.2.0
Requires-Dist: certifi==2025.8.3
Requires-Dist: cffi==2.0.0; platform_python_implementation != "PyPy"
Requires-Dist: charset-normalizer==3.4.3
Requires-Dist: click==8.3.0
Requires-Dist: colorama==0.4.6; sys_platform == "win32"
Requires-Dist: cryptography==46.0.1
Requires-Dist: distro==1.9.0
Requires-Dist: fastapi==0.117.1
Requires-Dist: frozenlist==1.7.0
Requires-Dist: gitdb==4.0.12
Requires-Dist: gitpython==3.1.45
Requires-Dist: h11==0.16.0
Requires-Dist: httpcore==1.0.9
Requires-Dist: httpx==0.28.1
Requires-Dist: idna==3.10
Requires-Dist: isodate==0.7.2
Requires-Dist: jinja2==3.1.6
Requires-Dist: jiter==0.11.0
Requires-Dist: jmespath==1.0.1
Requires-Dist: jsonschema-specifications==2025.9.1
Requires-Dist: jsonschema==4.25.1
Requires-Dist: markdown-it-py==4.0.0
Requires-Dist: markupsafe==3.0.2
Requires-Dist: mdurl==0.1.2
Requires-Dist: msal-extensions==1.3.1
Requires-Dist: msal==1.33.0
Requires-Dist: multidict==6.6.4
Requires-Dist: narwhals==2.5.0
Requires-Dist: numpy==2.3.3
Requires-Dist: openai==1.108.1
Requires-Dist: packaging==25.0
Requires-Dist: pandas==2.3.2
Requires-Dist: pillow==11.3.0
Requires-Dist: propcache==0.3.2
Requires-Dist: protobuf==6.32.1
Requires-Dist: pyarrow==21.0.0
Requires-Dist: pycparser==2.23; implementation_name != "PyPy" and platform_python_implementation != "PyPy"
Requires-Dist: pydantic-core==2.33.2
Requires-Dist: pydantic==2.11.9
Requires-Dist: pydeck==0.9.1
Requires-Dist: pygments==2.19.2
Requires-Dist: pyjwt==2.10.1
Requires-Dist: python-dateutil==2.9.0.post0
Requires-Dist: python-json-logger==3.3.0
Requires-Dist: pytz==2025.2
Requires-Dist: pyyaml==6.0.2
Requires-Dist: ragelo==0.1.6
Requires-Dist: referencing==0.36.2
Requires-Dist: requests==2.32.5
Requires-Dist: rich==14.1.0
Requires-Dist: rpds-py==0.27.1
Requires-Dist: s3transfer==0.14.0
Requires-Dist: shellingham==1.5.4
Requires-Dist: six==1.17.0
Requires-Dist: smmap==5.0.2
Requires-Dist: sniffio==1.3.1
Requires-Dist: sse-starlette==3.0.2
Requires-Dist: starlette==0.48.0
Requires-Dist: streamlit==1.49.1
Requires-Dist: tabulate==0.9.0
Requires-Dist: tenacity==9.1.2
Requires-Dist: toml==0.10.2
Requires-Dist: tornado==6.5.2
Requires-Dist: tqdm==4.67.1
Requires-Dist: typer==0.19.1
Requires-Dist: typing-extensions==4.15.0
Requires-Dist: typing-inspection==0.4.1
Requires-Dist: tzdata==2025.2
Requires-Dist: urllib3==2.5.0
Requires-Dist: uvicorn==0.36.0
Requires-Dist: watchdog==6.0.0; sys_platform != "darwin"
Requires-Dist: yarl==1.20.1
Provides-Extra: anthropic
Requires-Dist: aiofiles==24.1.0; extra == "anthropic"
Requires-Dist: aiohappyeyeballs==2.6.1; extra == "anthropic"
Requires-Dist: aiohttp==3.12.15; extra == "anthropic"
Requires-Dist: aiosignal==1.4.0; extra == "anthropic"
Requires-Dist: altair==5.5.0; extra == "anthropic"
Requires-Dist: annotated-types==0.7.0; extra == "anthropic"
Requires-Dist: anthropic==0.68.0; extra == "anthropic"
Requires-Dist: anyio==4.10.0; extra == "anthropic"
Requires-Dist: attrs==25.3.0; extra == "anthropic"
Requires-Dist: azure-core==1.35.1; extra == "anthropic"
Requires-Dist: azure-identity==1.25.0; extra == "anthropic"
Requires-Dist: azure-storage-blob==12.26.0; extra == "anthropic"
Requires-Dist: blinker==1.9.0; extra == "anthropic"
Requires-Dist: boto3==1.40.35; extra == "anthropic"
Requires-Dist: botocore==1.40.35; extra == "anthropic"
Requires-Dist: cachetools==6.2.0; extra == "anthropic"
Requires-Dist: certifi==2025.8.3; extra == "anthropic"
Requires-Dist: cffi==2.0.0; platform_python_implementation != "PyPy" and extra == "anthropic"
Requires-Dist: charset-normalizer==3.4.3; extra == "anthropic"
Requires-Dist: click==8.3.0; extra == "anthropic"
Requires-Dist: colorama==0.4.6; sys_platform == "win32" and extra == "anthropic"
Requires-Dist: cryptography==46.0.1; extra == "anthropic"
Requires-Dist: distro==1.9.0; extra == "anthropic"
Requires-Dist: docstring-parser==0.17.0; extra == "anthropic"
Requires-Dist: fastapi==0.117.1; extra == "anthropic"
Requires-Dist: frozenlist==1.7.0; extra == "anthropic"
Requires-Dist: gitdb==4.0.12; extra == "anthropic"
Requires-Dist: gitpython==3.1.45; extra == "anthropic"
Requires-Dist: h11==0.16.0; extra == "anthropic"
Requires-Dist: httpcore==1.0.9; extra == "anthropic"
Requires-Dist: httpx==0.28.1; extra == "anthropic"
Requires-Dist: idna==3.10; extra == "anthropic"
Requires-Dist: isodate==0.7.2; extra == "anthropic"
Requires-Dist: jinja2==3.1.6; extra == "anthropic"
Requires-Dist: jiter==0.11.0; extra == "anthropic"
Requires-Dist: jmespath==1.0.1; extra == "anthropic"
Requires-Dist: jsonschema-specifications==2025.9.1; extra == "anthropic"
Requires-Dist: jsonschema==4.25.1; extra == "anthropic"
Requires-Dist: markdown-it-py==4.0.0; extra == "anthropic"
Requires-Dist: markupsafe==3.0.2; extra == "anthropic"
Requires-Dist: mdurl==0.1.2; extra == "anthropic"
Requires-Dist: msal-extensions==1.3.1; extra == "anthropic"
Requires-Dist: msal==1.33.0; extra == "anthropic"
Requires-Dist: multidict==6.6.4; extra == "anthropic"
Requires-Dist: narwhals==2.5.0; extra == "anthropic"
Requires-Dist: numpy==2.3.3; extra == "anthropic"
Requires-Dist: openai==1.108.1; extra == "anthropic"
Requires-Dist: packaging==25.0; extra == "anthropic"
Requires-Dist: pandas==2.3.2; extra == "anthropic"
Requires-Dist: pillow==11.3.0; extra == "anthropic"
Requires-Dist: propcache==0.3.2; extra == "anthropic"
Requires-Dist: protobuf==6.32.1; extra == "anthropic"
Requires-Dist: pyarrow==21.0.0; extra == "anthropic"
Requires-Dist: pycparser==2.23; (implementation_name != "PyPy" and platform_python_implementation != "PyPy") and extra == "anthropic"
Requires-Dist: pydantic-core==2.33.2; extra == "anthropic"
Requires-Dist: pydantic==2.11.9; extra == "anthropic"
Requires-Dist: pydeck==0.9.1; extra == "anthropic"
Requires-Dist: pygments==2.19.2; extra == "anthropic"
Requires-Dist: pyjwt==2.10.1; extra == "anthropic"
Requires-Dist: python-dateutil==2.9.0.post0; extra == "anthropic"
Requires-Dist: python-json-logger==3.3.0; extra == "anthropic"
Requires-Dist: pytz==2025.2; extra == "anthropic"
Requires-Dist: pyyaml==6.0.2; extra == "anthropic"
Requires-Dist: ragelo==0.1.6; extra == "anthropic"
Requires-Dist: referencing==0.36.2; extra == "anthropic"
Requires-Dist: requests==2.32.5; extra == "anthropic"
Requires-Dist: rich==14.1.0; extra == "anthropic"
Requires-Dist: rpds-py==0.27.1; extra == "anthropic"
Requires-Dist: s3transfer==0.14.0; extra == "anthropic"
Requires-Dist: shellingham==1.5.4; extra == "anthropic"
Requires-Dist: six==1.17.0; extra == "anthropic"
Requires-Dist: smmap==5.0.2; extra == "anthropic"
Requires-Dist: sniffio==1.3.1; extra == "anthropic"
Requires-Dist: sse-starlette==3.0.2; extra == "anthropic"
Requires-Dist: starlette==0.48.0; extra == "anthropic"
Requires-Dist: streamlit==1.49.1; extra == "anthropic"
Requires-Dist: tabulate==0.9.0; extra == "anthropic"
Requires-Dist: tenacity==9.1.2; extra == "anthropic"
Requires-Dist: toml==0.10.2; extra == "anthropic"
Requires-Dist: tornado==6.5.2; extra == "anthropic"
Requires-Dist: tqdm==4.67.1; extra == "anthropic"
Requires-Dist: typer==0.19.1; extra == "anthropic"
Requires-Dist: typing-extensions==4.15.0; extra == "anthropic"
Requires-Dist: typing-inspection==0.4.1; extra == "anthropic"
Requires-Dist: tzdata==2025.2; extra == "anthropic"
Requires-Dist: urllib3==2.5.0; extra == "anthropic"
Requires-Dist: uvicorn==0.36.0; extra == "anthropic"
Requires-Dist: watchdog==6.0.0; sys_platform != "darwin" and extra == "anthropic"
Requires-Dist: yarl==1.20.1; extra == "anthropic"
Provides-Extra: bedrock
Requires-Dist: aiofiles==24.1.0; extra == "bedrock"
Requires-Dist: aiohappyeyeballs==2.6.1; extra == "bedrock"
Requires-Dist: aiohttp==3.12.15; extra == "bedrock"
Requires-Dist: aiosignal==1.4.0; extra == "bedrock"
Requires-Dist: altair==5.5.0; extra == "bedrock"
Requires-Dist: annotated-types==0.7.0; extra == "bedrock"
Requires-Dist: anthropic==0.68.0; extra == "bedrock"
Requires-Dist: anyio==4.10.0; extra == "bedrock"
Requires-Dist: attrs==25.3.0; extra == "bedrock"
Requires-Dist: azure-core==1.35.1; extra == "bedrock"
Requires-Dist: azure-identity==1.25.0; extra == "bedrock"
Requires-Dist: azure-storage-blob==12.26.0; extra == "bedrock"
Requires-Dist: blinker==1.9.0; extra == "bedrock"
Requires-Dist: boto3==1.40.35; extra == "bedrock"
Requires-Dist: botocore==1.40.35; extra == "bedrock"
Requires-Dist: cachetools==6.2.0; extra == "bedrock"
Requires-Dist: certifi==2025.8.3; extra == "bedrock"
Requires-Dist: cffi==2.0.0; platform_python_implementation != "PyPy" and extra == "bedrock"
Requires-Dist: charset-normalizer==3.4.3; extra == "bedrock"
Requires-Dist: click==8.3.0; extra == "bedrock"
Requires-Dist: colorama==0.4.6; sys_platform == "win32" and extra == "bedrock"
Requires-Dist: cryptography==46.0.1; extra == "bedrock"
Requires-Dist: distro==1.9.0; extra == "bedrock"
Requires-Dist: docstring-parser==0.17.0; extra == "bedrock"
Requires-Dist: fastapi==0.117.1; extra == "bedrock"
Requires-Dist: frozenlist==1.7.0; extra == "bedrock"
Requires-Dist: gitdb==4.0.12; extra == "bedrock"
Requires-Dist: gitpython==3.1.45; extra == "bedrock"
Requires-Dist: h11==0.16.0; extra == "bedrock"
Requires-Dist: httpcore==1.0.9; extra == "bedrock"
Requires-Dist: httpx==0.28.1; extra == "bedrock"
Requires-Dist: idna==3.10; extra == "bedrock"
Requires-Dist: isodate==0.7.2; extra == "bedrock"
Requires-Dist: jinja2==3.1.6; extra == "bedrock"
Requires-Dist: jiter==0.11.0; extra == "bedrock"
Requires-Dist: jmespath==1.0.1; extra == "bedrock"
Requires-Dist: jsonschema-specifications==2025.9.1; extra == "bedrock"
Requires-Dist: jsonschema==4.25.1; extra == "bedrock"
Requires-Dist: markdown-it-py==4.0.0; extra == "bedrock"
Requires-Dist: markupsafe==3.0.2; extra == "bedrock"
Requires-Dist: mdurl==0.1.2; extra == "bedrock"
Requires-Dist: msal-extensions==1.3.1; extra == "bedrock"
Requires-Dist: msal==1.33.0; extra == "bedrock"
Requires-Dist: multidict==6.6.4; extra == "bedrock"
Requires-Dist: narwhals==2.5.0; extra == "bedrock"
Requires-Dist: numpy==2.3.3; extra == "bedrock"
Requires-Dist: openai==1.108.1; extra == "bedrock"
Requires-Dist: packaging==25.0; extra == "bedrock"
Requires-Dist: pandas==2.3.2; extra == "bedrock"
Requires-Dist: pillow==11.3.0; extra == "bedrock"
Requires-Dist: propcache==0.3.2; extra == "bedrock"
Requires-Dist: protobuf==6.32.1; extra == "bedrock"
Requires-Dist: pyarrow==21.0.0; extra == "bedrock"
Requires-Dist: pycparser==2.23; (implementation_name != "PyPy" and platform_python_implementation != "PyPy") and extra == "bedrock"
Requires-Dist: pydantic-core==2.33.2; extra == "bedrock"
Requires-Dist: pydantic==2.11.9; extra == "bedrock"
Requires-Dist: pydeck==0.9.1; extra == "bedrock"
Requires-Dist: pygments==2.19.2; extra == "bedrock"
Requires-Dist: pyjwt==2.10.1; extra == "bedrock"
Requires-Dist: python-dateutil==2.9.0.post0; extra == "bedrock"
Requires-Dist: python-json-logger==3.3.0; extra == "bedrock"
Requires-Dist: pytz==2025.2; extra == "bedrock"
Requires-Dist: pyyaml==6.0.2; extra == "bedrock"
Requires-Dist: ragelo==0.1.6; extra == "bedrock"
Requires-Dist: referencing==0.36.2; extra == "bedrock"
Requires-Dist: requests==2.32.5; extra == "bedrock"
Requires-Dist: rich==14.1.0; extra == "bedrock"
Requires-Dist: rpds-py==0.27.1; extra == "bedrock"
Requires-Dist: s3transfer==0.14.0; extra == "bedrock"
Requires-Dist: shellingham==1.5.4; extra == "bedrock"
Requires-Dist: six==1.17.0; extra == "bedrock"
Requires-Dist: smmap==5.0.2; extra == "bedrock"
Requires-Dist: sniffio==1.3.1; extra == "bedrock"
Requires-Dist: sse-starlette==3.0.2; extra == "bedrock"
Requires-Dist: starlette==0.48.0; extra == "bedrock"
Requires-Dist: streamlit==1.49.1; extra == "bedrock"
Requires-Dist: tabulate==0.9.0; extra == "bedrock"
Requires-Dist: tenacity==9.1.2; extra == "bedrock"
Requires-Dist: toml==0.10.2; extra == "bedrock"
Requires-Dist: tornado==6.5.2; extra == "bedrock"
Requires-Dist: tqdm==4.67.1; extra == "bedrock"
Requires-Dist: typer==0.19.1; extra == "bedrock"
Requires-Dist: typing-extensions==4.15.0; extra == "bedrock"
Requires-Dist: typing-inspection==0.4.1; extra == "bedrock"
Requires-Dist: tzdata==2025.2; extra == "bedrock"
Requires-Dist: urllib3==2.5.0; extra == "bedrock"
Requires-Dist: uvicorn==0.36.0; extra == "bedrock"
Requires-Dist: watchdog==6.0.0; sys_platform != "darwin" and extra == "bedrock"
Requires-Dist: yarl==1.20.1; extra == "bedrock"
Provides-Extra: langchain
Requires-Dist: aiofiles==24.1.0; extra == "langchain"
Requires-Dist: aiohappyeyeballs==2.6.1; extra == "langchain"
Requires-Dist: aiohttp==3.12.15; extra == "langchain"
Requires-Dist: aiosignal==1.4.0; extra == "langchain"
Requires-Dist: altair==5.5.0; extra == "langchain"
Requires-Dist: annotated-types==0.7.0; extra == "langchain"
Requires-Dist: anyio==4.10.0; extra == "langchain"
Requires-Dist: attrs==25.3.0; extra == "langchain"
Requires-Dist: azure-core==1.35.1; extra == "langchain"
Requires-Dist: azure-identity==1.25.0; extra == "langchain"
Requires-Dist: azure-storage-blob==12.26.0; extra == "langchain"
Requires-Dist: blinker==1.9.0; extra == "langchain"
Requires-Dist: boto3==1.40.35; extra == "langchain"
Requires-Dist: botocore==1.40.35; extra == "langchain"
Requires-Dist: cachetools==6.2.0; extra == "langchain"
Requires-Dist: certifi==2025.8.3; extra == "langchain"
Requires-Dist: cffi==2.0.0; platform_python_implementation != "PyPy" and extra == "langchain"
Requires-Dist: charset-normalizer==3.4.3; extra == "langchain"
Requires-Dist: click==8.3.0; extra == "langchain"
Requires-Dist: colorama==0.4.6; sys_platform == "win32" and extra == "langchain"
Requires-Dist: cryptography==46.0.1; extra == "langchain"
Requires-Dist: distro==1.9.0; extra == "langchain"
Requires-Dist: fastapi==0.117.1; extra == "langchain"
Requires-Dist: frozenlist==1.7.0; extra == "langchain"
Requires-Dist: gitdb==4.0.12; extra == "langchain"
Requires-Dist: gitpython==3.1.45; extra == "langchain"
Requires-Dist: greenlet==3.2.4; ((python_full_version < "3.14" and platform_machine == "AMD64") or (python_full_version < "3.14" and platform_machine == "WIN32") or (python_full_version < "3.14" and platform_machine == "aarch64") or (python_full_version < "3.14" and platform_machine == "amd64") or (python_full_version < "3.14" and platform_machine == "ppc64le") or (python_full_version < "3.14" and platform_machine == "win32") or (python_full_version < "3.14" and platform_machine == "x86_64")) an
Requires-Dist: h11==0.16.0; extra == "langchain"
Requires-Dist: httpcore==1.0.9; extra == "langchain"
Requires-Dist: httpx==0.28.1; extra == "langchain"
Requires-Dist: idna==3.10; extra == "langchain"
Requires-Dist: isodate==0.7.2; extra == "langchain"
Requires-Dist: jinja2==3.1.6; extra == "langchain"
Requires-Dist: jiter==0.11.0; extra == "langchain"
Requires-Dist: jmespath==1.0.1; extra == "langchain"
Requires-Dist: jsonpatch==1.33; extra == "langchain"
Requires-Dist: jsonpointer==3.0.0; extra == "langchain"
Requires-Dist: jsonschema-specifications==2025.9.1; extra == "langchain"
Requires-Dist: jsonschema==4.25.1; extra == "langchain"
Requires-Dist: langchain-core==0.3.76; extra == "langchain"
Requires-Dist: langchain-text-splitters==0.3.11; extra == "langchain"
Requires-Dist: langchain==0.3.27; extra == "langchain"
Requires-Dist: langsmith==0.4.29; extra == "langchain"
Requires-Dist: markdown-it-py==4.0.0; extra == "langchain"
Requires-Dist: markupsafe==3.0.2; extra == "langchain"
Requires-Dist: mdurl==0.1.2; extra == "langchain"
Requires-Dist: msal-extensions==1.3.1; extra == "langchain"
Requires-Dist: msal==1.33.0; extra == "langchain"
Requires-Dist: multidict==6.6.4; extra == "langchain"
Requires-Dist: narwhals==2.5.0; extra == "langchain"
Requires-Dist: numpy==2.3.3; extra == "langchain"
Requires-Dist: openai==1.108.1; extra == "langchain"
Requires-Dist: orjson==3.11.3; platform_python_implementation != "PyPy" and extra == "langchain"
Requires-Dist: packaging==25.0; extra == "langchain"
Requires-Dist: pandas==2.3.2; extra == "langchain"
Requires-Dist: pillow==11.3.0; extra == "langchain"
Requires-Dist: propcache==0.3.2; extra == "langchain"
Requires-Dist: protobuf==6.32.1; extra == "langchain"
Requires-Dist: pyarrow==21.0.0; extra == "langchain"
Requires-Dist: pycparser==2.23; (implementation_name != "PyPy" and platform_python_implementation != "PyPy") and extra == "langchain"
Requires-Dist: pydantic-core==2.33.2; extra == "langchain"
Requires-Dist: pydantic==2.11.9; extra == "langchain"
Requires-Dist: pydeck==0.9.1; extra == "langchain"
Requires-Dist: pygments==2.19.2; extra == "langchain"
Requires-Dist: pyjwt==2.10.1; extra == "langchain"
Requires-Dist: python-dateutil==2.9.0.post0; extra == "langchain"
Requires-Dist: python-json-logger==3.3.0; extra == "langchain"
Requires-Dist: pytz==2025.2; extra == "langchain"
Requires-Dist: pyyaml==6.0.2; extra == "langchain"
Requires-Dist: ragelo==0.1.6; extra == "langchain"
Requires-Dist: referencing==0.36.2; extra == "langchain"
Requires-Dist: requests-toolbelt==1.0.0; extra == "langchain"
Requires-Dist: requests==2.32.5; extra == "langchain"
Requires-Dist: rich==14.1.0; extra == "langchain"
Requires-Dist: rpds-py==0.27.1; extra == "langchain"
Requires-Dist: s3transfer==0.14.0; extra == "langchain"
Requires-Dist: shellingham==1.5.4; extra == "langchain"
Requires-Dist: six==1.17.0; extra == "langchain"
Requires-Dist: smmap==5.0.2; extra == "langchain"
Requires-Dist: sniffio==1.3.1; extra == "langchain"
Requires-Dist: sqlalchemy==2.0.43; extra == "langchain"
Requires-Dist: sse-starlette==3.0.2; extra == "langchain"
Requires-Dist: starlette==0.48.0; extra == "langchain"
Requires-Dist: streamlit==1.49.1; extra == "langchain"
Requires-Dist: tabulate==0.9.0; extra == "langchain"
Requires-Dist: tenacity==9.1.2; extra == "langchain"
Requires-Dist: toml==0.10.2; extra == "langchain"
Requires-Dist: tornado==6.5.2; extra == "langchain"
Requires-Dist: tqdm==4.67.1; extra == "langchain"
Requires-Dist: typer==0.19.1; extra == "langchain"
Requires-Dist: typing-extensions==4.15.0; extra == "langchain"
Requires-Dist: typing-inspection==0.4.1; extra == "langchain"
Requires-Dist: tzdata==2025.2; extra == "langchain"
Requires-Dist: urllib3==2.5.0; extra == "langchain"
Requires-Dist: uvicorn==0.36.0; extra == "langchain"
Requires-Dist: watchdog==6.0.0; sys_platform != "darwin" and extra == "langchain"
Requires-Dist: yarl==1.20.1; extra == "langchain"
Requires-Dist: zstandard==0.25.0; extra == "langchain"
Provides-Extra: langchain-anthropic
Requires-Dist: aiofiles==24.1.0; extra == "langchain-anthropic"
Requires-Dist: aiohappyeyeballs==2.6.1; extra == "langchain-anthropic"
Requires-Dist: aiohttp==3.12.15; extra == "langchain-anthropic"
Requires-Dist: aiosignal==1.4.0; extra == "langchain-anthropic"
Requires-Dist: altair==5.5.0; extra == "langchain-anthropic"
Requires-Dist: annotated-types==0.7.0; extra == "langchain-anthropic"
Requires-Dist: anthropic==0.68.0; extra == "langchain-anthropic"
Requires-Dist: anyio==4.10.0; extra == "langchain-anthropic"
Requires-Dist: attrs==25.3.0; extra == "langchain-anthropic"
Requires-Dist: azure-core==1.35.1; extra == "langchain-anthropic"
Requires-Dist: azure-identity==1.25.0; extra == "langchain-anthropic"
Requires-Dist: azure-storage-blob==12.26.0; extra == "langchain-anthropic"
Requires-Dist: blinker==1.9.0; extra == "langchain-anthropic"
Requires-Dist: boto3==1.40.35; extra == "langchain-anthropic"
Requires-Dist: botocore==1.40.35; extra == "langchain-anthropic"
Requires-Dist: cachetools==6.2.0; extra == "langchain-anthropic"
Requires-Dist: certifi==2025.8.3; extra == "langchain-anthropic"
Requires-Dist: cffi==2.0.0; platform_python_implementation != "PyPy" and extra == "langchain-anthropic"
Requires-Dist: charset-normalizer==3.4.3; extra == "langchain-anthropic"
Requires-Dist: click==8.3.0; extra == "langchain-anthropic"
Requires-Dist: colorama==0.4.6; sys_platform == "win32" and extra == "langchain-anthropic"
Requires-Dist: cryptography==46.0.1; extra == "langchain-anthropic"
Requires-Dist: distro==1.9.0; extra == "langchain-anthropic"
Requires-Dist: docstring-parser==0.17.0; extra == "langchain-anthropic"
Requires-Dist: fastapi==0.117.1; extra == "langchain-anthropic"
Requires-Dist: frozenlist==1.7.0; extra == "langchain-anthropic"
Requires-Dist: gitdb==4.0.12; extra == "langchain-anthropic"
Requires-Dist: gitpython==3.1.45; extra == "langchain-anthropic"
Requires-Dist: h11==0.16.0; extra == "langchain-anthropic"
Requires-Dist: httpcore==1.0.9; extra == "langchain-anthropic"
Requires-Dist: httpx==0.28.1; extra == "langchain-anthropic"
Requires-Dist: idna==3.10; extra == "langchain-anthropic"
Requires-Dist: isodate==0.7.2; extra == "langchain-anthropic"
Requires-Dist: jinja2==3.1.6; extra == "langchain-anthropic"
Requires-Dist: jiter==0.11.0; extra == "langchain-anthropic"
Requires-Dist: jmespath==1.0.1; extra == "langchain-anthropic"
Requires-Dist: jsonpatch==1.33; extra == "langchain-anthropic"
Requires-Dist: jsonpointer==3.0.0; extra == "langchain-anthropic"
Requires-Dist: jsonschema-specifications==2025.9.1; extra == "langchain-anthropic"
Requires-Dist: jsonschema==4.25.1; extra == "langchain-anthropic"
Requires-Dist: langchain-anthropic==0.3.20; extra == "langchain-anthropic"
Requires-Dist: langchain-core==0.3.76; extra == "langchain-anthropic"
Requires-Dist: langsmith==0.4.29; extra == "langchain-anthropic"
Requires-Dist: markdown-it-py==4.0.0; extra == "langchain-anthropic"
Requires-Dist: markupsafe==3.0.2; extra == "langchain-anthropic"
Requires-Dist: mdurl==0.1.2; extra == "langchain-anthropic"
Requires-Dist: msal-extensions==1.3.1; extra == "langchain-anthropic"
Requires-Dist: msal==1.33.0; extra == "langchain-anthropic"
Requires-Dist: multidict==6.6.4; extra == "langchain-anthropic"
Requires-Dist: narwhals==2.5.0; extra == "langchain-anthropic"
Requires-Dist: numpy==2.3.3; extra == "langchain-anthropic"
Requires-Dist: openai==1.108.1; extra == "langchain-anthropic"
Requires-Dist: orjson==3.11.3; platform_python_implementation != "PyPy" and extra == "langchain-anthropic"
Requires-Dist: packaging==25.0; extra == "langchain-anthropic"
Requires-Dist: pandas==2.3.2; extra == "langchain-anthropic"
Requires-Dist: pillow==11.3.0; extra == "langchain-anthropic"
Requires-Dist: propcache==0.3.2; extra == "langchain-anthropic"
Requires-Dist: protobuf==6.32.1; extra == "langchain-anthropic"
Requires-Dist: pyarrow==21.0.0; extra == "langchain-anthropic"
Requires-Dist: pycparser==2.23; (implementation_name != "PyPy" and platform_python_implementation != "PyPy") and extra == "langchain-anthropic"
Requires-Dist: pydantic-core==2.33.2; extra == "langchain-anthropic"
Requires-Dist: pydantic==2.11.9; extra == "langchain-anthropic"
Requires-Dist: pydeck==0.9.1; extra == "langchain-anthropic"
Requires-Dist: pygments==2.19.2; extra == "langchain-anthropic"
Requires-Dist: pyjwt==2.10.1; extra == "langchain-anthropic"
Requires-Dist: python-dateutil==2.9.0.post0; extra == "langchain-anthropic"
Requires-Dist: python-json-logger==3.3.0; extra == "langchain-anthropic"
Requires-Dist: pytz==2025.2; extra == "langchain-anthropic"
Requires-Dist: pyyaml==6.0.2; extra == "langchain-anthropic"
Requires-Dist: ragelo==0.1.6; extra == "langchain-anthropic"
Requires-Dist: referencing==0.36.2; extra == "langchain-anthropic"
Requires-Dist: requests-toolbelt==1.0.0; extra == "langchain-anthropic"
Requires-Dist: requests==2.32.5; extra == "langchain-anthropic"
Requires-Dist: rich==14.1.0; extra == "langchain-anthropic"
Requires-Dist: rpds-py==0.27.1; extra == "langchain-anthropic"
Requires-Dist: s3transfer==0.14.0; extra == "langchain-anthropic"
Requires-Dist: shellingham==1.5.4; extra == "langchain-anthropic"
Requires-Dist: six==1.17.0; extra == "langchain-anthropic"
Requires-Dist: smmap==5.0.2; extra == "langchain-anthropic"
Requires-Dist: sniffio==1.3.1; extra == "langchain-anthropic"
Requires-Dist: sse-starlette==3.0.2; extra == "langchain-anthropic"
Requires-Dist: starlette==0.48.0; extra == "langchain-anthropic"
Requires-Dist: streamlit==1.49.1; extra == "langchain-anthropic"
Requires-Dist: tabulate==0.9.0; extra == "langchain-anthropic"
Requires-Dist: tenacity==9.1.2; extra == "langchain-anthropic"
Requires-Dist: toml==0.10.2; extra == "langchain-anthropic"
Requires-Dist: tornado==6.5.2; extra == "langchain-anthropic"
Requires-Dist: tqdm==4.67.1; extra == "langchain-anthropic"
Requires-Dist: typer==0.19.1; extra == "langchain-anthropic"
Requires-Dist: typing-extensions==4.15.0; extra == "langchain-anthropic"
Requires-Dist: typing-inspection==0.4.1; extra == "langchain-anthropic"
Requires-Dist: tzdata==2025.2; extra == "langchain-anthropic"
Requires-Dist: urllib3==2.5.0; extra == "langchain-anthropic"
Requires-Dist: uvicorn==0.36.0; extra == "langchain-anthropic"
Requires-Dist: watchdog==6.0.0; sys_platform != "darwin" and extra == "langchain-anthropic"
Requires-Dist: yarl==1.20.1; extra == "langchain-anthropic"
Requires-Dist: zstandard==0.25.0; extra == "langchain-anthropic"
Provides-Extra: langchain-aws
Requires-Dist: aiofiles==24.1.0; extra == "langchain-aws"
Requires-Dist: aiohappyeyeballs==2.6.1; extra == "langchain-aws"
Requires-Dist: aiohttp==3.12.15; extra == "langchain-aws"
Requires-Dist: aiosignal==1.4.0; extra == "langchain-aws"
Requires-Dist: altair==5.5.0; extra == "langchain-aws"
Requires-Dist: annotated-types==0.7.0; extra == "langchain-aws"
Requires-Dist: anyio==4.10.0; extra == "langchain-aws"
Requires-Dist: attrs==25.3.0; extra == "langchain-aws"
Requires-Dist: azure-core==1.35.1; extra == "langchain-aws"
Requires-Dist: azure-identity==1.25.0; extra == "langchain-aws"
Requires-Dist: azure-storage-blob==12.26.0; extra == "langchain-aws"
Requires-Dist: blinker==1.9.0; extra == "langchain-aws"
Requires-Dist: boto3==1.40.35; extra == "langchain-aws"
Requires-Dist: botocore==1.40.35; extra == "langchain-aws"
Requires-Dist: cachetools==6.2.0; extra == "langchain-aws"
Requires-Dist: certifi==2025.8.3; extra == "langchain-aws"
Requires-Dist: cffi==2.0.0; platform_python_implementation != "PyPy" and extra == "langchain-aws"
Requires-Dist: charset-normalizer==3.4.3; extra == "langchain-aws"
Requires-Dist: click==8.3.0; extra == "langchain-aws"
Requires-Dist: colorama==0.4.6; sys_platform == "win32" and extra == "langchain-aws"
Requires-Dist: cryptography==46.0.1; extra == "langchain-aws"
Requires-Dist: distro==1.9.0; extra == "langchain-aws"
Requires-Dist: fastapi==0.117.1; extra == "langchain-aws"
Requires-Dist: frozenlist==1.7.0; extra == "langchain-aws"
Requires-Dist: gitdb==4.0.12; extra == "langchain-aws"
Requires-Dist: gitpython==3.1.45; extra == "langchain-aws"
Requires-Dist: h11==0.16.0; extra == "langchain-aws"
Requires-Dist: httpcore==1.0.9; extra == "langchain-aws"
Requires-Dist: httpx==0.28.1; extra == "langchain-aws"
Requires-Dist: idna==3.10; extra == "langchain-aws"
Requires-Dist: isodate==0.7.2; extra == "langchain-aws"
Requires-Dist: jinja2==3.1.6; extra == "langchain-aws"
Requires-Dist: jiter==0.11.0; extra == "langchain-aws"
Requires-Dist: jmespath==1.0.1; extra == "langchain-aws"
Requires-Dist: jsonpatch==1.33; extra == "langchain-aws"
Requires-Dist: jsonpointer==3.0.0; extra == "langchain-aws"
Requires-Dist: jsonschema-specifications==2025.9.1; extra == "langchain-aws"
Requires-Dist: jsonschema==4.25.1; extra == "langchain-aws"
Requires-Dist: langchain-aws==0.2.33; extra == "langchain-aws"
Requires-Dist: langchain-core==0.3.76; extra == "langchain-aws"
Requires-Dist: langsmith==0.4.29; extra == "langchain-aws"
Requires-Dist: markdown-it-py==4.0.0; extra == "langchain-aws"
Requires-Dist: markupsafe==3.0.2; extra == "langchain-aws"
Requires-Dist: mdurl==0.1.2; extra == "langchain-aws"
Requires-Dist: msal-extensions==1.3.1; extra == "langchain-aws"
Requires-Dist: msal==1.33.0; extra == "langchain-aws"
Requires-Dist: multidict==6.6.4; extra == "langchain-aws"
Requires-Dist: narwhals==2.5.0; extra == "langchain-aws"
Requires-Dist: numpy==2.3.3; extra == "langchain-aws"
Requires-Dist: openai==1.108.1; extra == "langchain-aws"
Requires-Dist: orjson==3.11.3; platform_python_implementation != "PyPy" and extra == "langchain-aws"
Requires-Dist: packaging==25.0; extra == "langchain-aws"
Requires-Dist: pandas==2.3.2; extra == "langchain-aws"
Requires-Dist: pillow==11.3.0; extra == "langchain-aws"
Requires-Dist: propcache==0.3.2; extra == "langchain-aws"
Requires-Dist: protobuf==6.32.1; extra == "langchain-aws"
Requires-Dist: pyarrow==21.0.0; extra == "langchain-aws"
Requires-Dist: pycparser==2.23; (implementation_name != "PyPy" and platform_python_implementation != "PyPy") and extra == "langchain-aws"
Requires-Dist: pydantic-core==2.33.2; extra == "langchain-aws"
Requires-Dist: pydantic==2.11.9; extra == "langchain-aws"
Requires-Dist: pydeck==0.9.1; extra == "langchain-aws"
Requires-Dist: pygments==2.19.2; extra == "langchain-aws"
Requires-Dist: pyjwt==2.10.1; extra == "langchain-aws"
Requires-Dist: python-dateutil==2.9.0.post0; extra == "langchain-aws"
Requires-Dist: python-json-logger==3.3.0; extra == "langchain-aws"
Requires-Dist: pytz==2025.2; extra == "langchain-aws"
Requires-Dist: pyyaml==6.0.2; extra == "langchain-aws"
Requires-Dist: ragelo==0.1.6; extra == "langchain-aws"
Requires-Dist: referencing==0.36.2; extra == "langchain-aws"
Requires-Dist: requests-toolbelt==1.0.0; extra == "langchain-aws"
Requires-Dist: requests==2.32.5; extra == "langchain-aws"
Requires-Dist: rich==14.1.0; extra == "langchain-aws"
Requires-Dist: rpds-py==0.27.1; extra == "langchain-aws"
Requires-Dist: s3transfer==0.14.0; extra == "langchain-aws"
Requires-Dist: shellingham==1.5.4; extra == "langchain-aws"
Requires-Dist: six==1.17.0; extra == "langchain-aws"
Requires-Dist: smmap==5.0.2; extra == "langchain-aws"
Requires-Dist: sniffio==1.3.1; extra == "langchain-aws"
Requires-Dist: sse-starlette==3.0.2; extra == "langchain-aws"
Requires-Dist: starlette==0.48.0; extra == "langchain-aws"
Requires-Dist: streamlit==1.49.1; extra == "langchain-aws"
Requires-Dist: tabulate==0.9.0; extra == "langchain-aws"
Requires-Dist: tenacity==9.1.2; extra == "langchain-aws"
Requires-Dist: toml==0.10.2; extra == "langchain-aws"
Requires-Dist: tornado==6.5.2; extra == "langchain-aws"
Requires-Dist: tqdm==4.67.1; extra == "langchain-aws"
Requires-Dist: typer==0.19.1; extra == "langchain-aws"
Requires-Dist: typing-extensions==4.15.0; extra == "langchain-aws"
Requires-Dist: typing-inspection==0.4.1; extra == "langchain-aws"
Requires-Dist: tzdata==2025.2; extra == "langchain-aws"
Requires-Dist: urllib3==2.5.0; extra == "langchain-aws"
Requires-Dist: uvicorn==0.36.0; extra == "langchain-aws"
Requires-Dist: watchdog==6.0.0; sys_platform != "darwin" and extra == "langchain-aws"
Requires-Dist: yarl==1.20.1; extra == "langchain-aws"
Requires-Dist: zstandard==0.25.0; extra == "langchain-aws"
Provides-Extra: langchain-openai
Requires-Dist: aiofiles==24.1.0; extra == "langchain-openai"
Requires-Dist: aiohappyeyeballs==2.6.1; extra == "langchain-openai"
Requires-Dist: aiohttp==3.12.15; extra == "langchain-openai"
Requires-Dist: aiosignal==1.4.0; extra == "langchain-openai"
Requires-Dist: altair==5.5.0; extra == "langchain-openai"
Requires-Dist: annotated-types==0.7.0; extra == "langchain-openai"
Requires-Dist: anyio==4.10.0; extra == "langchain-openai"
Requires-Dist: attrs==25.3.0; extra == "langchain-openai"
Requires-Dist: azure-core==1.35.1; extra == "langchain-openai"
Requires-Dist: azure-identity==1.25.0; extra == "langchain-openai"
Requires-Dist: azure-storage-blob==12.26.0; extra == "langchain-openai"
Requires-Dist: blinker==1.9.0; extra == "langchain-openai"
Requires-Dist: boto3==1.40.35; extra == "langchain-openai"
Requires-Dist: botocore==1.40.35; extra == "langchain-openai"
Requires-Dist: cachetools==6.2.0; extra == "langchain-openai"
Requires-Dist: certifi==2025.8.3; extra == "langchain-openai"
Requires-Dist: cffi==2.0.0; platform_python_implementation != "PyPy" and extra == "langchain-openai"
Requires-Dist: charset-normalizer==3.4.3; extra == "langchain-openai"
Requires-Dist: click==8.3.0; extra == "langchain-openai"
Requires-Dist: colorama==0.4.6; sys_platform == "win32" and extra == "langchain-openai"
Requires-Dist: cryptography==46.0.1; extra == "langchain-openai"
Requires-Dist: distro==1.9.0; extra == "langchain-openai"
Requires-Dist: fastapi==0.117.1; extra == "langchain-openai"
Requires-Dist: frozenlist==1.7.0; extra == "langchain-openai"
Requires-Dist: gitdb==4.0.12; extra == "langchain-openai"
Requires-Dist: gitpython==3.1.45; extra == "langchain-openai"
Requires-Dist: h11==0.16.0; extra == "langchain-openai"
Requires-Dist: httpcore==1.0.9; extra == "langchain-openai"
Requires-Dist: httpx==0.28.1; extra == "langchain-openai"
Requires-Dist: idna==3.10; extra == "langchain-openai"
Requires-Dist: isodate==0.7.2; extra == "langchain-openai"
Requires-Dist: jinja2==3.1.6; extra == "langchain-openai"
Requires-Dist: jiter==0.11.0; extra == "langchain-openai"
Requires-Dist: jmespath==1.0.1; extra == "langchain-openai"
Requires-Dist: jsonpatch==1.33; extra == "langchain-openai"
Requires-Dist: jsonpointer==3.0.0; extra == "langchain-openai"
Requires-Dist: jsonschema-specifications==2025.9.1; extra == "langchain-openai"
Requires-Dist: jsonschema==4.25.1; extra == "langchain-openai"
Requires-Dist: langchain-core==0.3.76; extra == "langchain-openai"
Requires-Dist: langchain-openai==0.3.33; extra == "langchain-openai"
Requires-Dist: langsmith==0.4.29; extra == "langchain-openai"
Requires-Dist: markdown-it-py==4.0.0; extra == "langchain-openai"
Requires-Dist: markupsafe==3.0.2; extra == "langchain-openai"
Requires-Dist: mdurl==0.1.2; extra == "langchain-openai"
Requires-Dist: msal-extensions==1.3.1; extra == "langchain-openai"
Requires-Dist: msal==1.33.0; extra == "langchain-openai"
Requires-Dist: multidict==6.6.4; extra == "langchain-openai"
Requires-Dist: narwhals==2.5.0; extra == "langchain-openai"
Requires-Dist: numpy==2.3.3; extra == "langchain-openai"
Requires-Dist: openai==1.108.1; extra == "langchain-openai"
Requires-Dist: orjson==3.11.3; platform_python_implementation != "PyPy" and extra == "langchain-openai"
Requires-Dist: packaging==25.0; extra == "langchain-openai"
Requires-Dist: pandas==2.3.2; extra == "langchain-openai"
Requires-Dist: pillow==11.3.0; extra == "langchain-openai"
Requires-Dist: propcache==0.3.2; extra == "langchain-openai"
Requires-Dist: protobuf==6.32.1; extra == "langchain-openai"
Requires-Dist: pyarrow==21.0.0; extra == "langchain-openai"
Requires-Dist: pycparser==2.23; (implementation_name != "PyPy" and platform_python_implementation != "PyPy") and extra == "langchain-openai"
Requires-Dist: pydantic-core==2.33.2; extra == "langchain-openai"
Requires-Dist: pydantic==2.11.9; extra == "langchain-openai"
Requires-Dist: pydeck==0.9.1; extra == "langchain-openai"
Requires-Dist: pygments==2.19.2; extra == "langchain-openai"
Requires-Dist: pyjwt==2.10.1; extra == "langchain-openai"
Requires-Dist: python-dateutil==2.9.0.post0; extra == "langchain-openai"
Requires-Dist: python-json-logger==3.3.0; extra == "langchain-openai"
Requires-Dist: pytz==2025.2; extra == "langchain-openai"
Requires-Dist: pyyaml==6.0.2; extra == "langchain-openai"
Requires-Dist: ragelo==0.1.6; extra == "langchain-openai"
Requires-Dist: referencing==0.36.2; extra == "langchain-openai"
Requires-Dist: regex==2025.9.18; extra == "langchain-openai"
Requires-Dist: requests-toolbelt==1.0.0; extra == "langchain-openai"
Requires-Dist: requests==2.32.5; extra == "langchain-openai"
Requires-Dist: rich==14.1.0; extra == "langchain-openai"
Requires-Dist: rpds-py==0.27.1; extra == "langchain-openai"
Requires-Dist: s3transfer==0.14.0; extra == "langchain-openai"
Requires-Dist: shellingham==1.5.4; extra == "langchain-openai"
Requires-Dist: six==1.17.0; extra == "langchain-openai"
Requires-Dist: smmap==5.0.2; extra == "langchain-openai"
Requires-Dist: sniffio==1.3.1; extra == "langchain-openai"
Requires-Dist: sse-starlette==3.0.2; extra == "langchain-openai"
Requires-Dist: starlette==0.48.0; extra == "langchain-openai"
Requires-Dist: streamlit==1.49.1; extra == "langchain-openai"
Requires-Dist: tabulate==0.9.0; extra == "langchain-openai"
Requires-Dist: tenacity==9.1.2; extra == "langchain-openai"
Requires-Dist: tiktoken==0.11.0; extra == "langchain-openai"
Requires-Dist: toml==0.10.2; extra == "langchain-openai"
Requires-Dist: tornado==6.5.2; extra == "langchain-openai"
Requires-Dist: tqdm==4.67.1; extra == "langchain-openai"
Requires-Dist: typer==0.19.1; extra == "langchain-openai"
Requires-Dist: typing-extensions==4.15.0; extra == "langchain-openai"
Requires-Dist: typing-inspection==0.4.1; extra == "langchain-openai"
Requires-Dist: tzdata==2025.2; extra == "langchain-openai"
Requires-Dist: urllib3==2.5.0; extra == "langchain-openai"
Requires-Dist: uvicorn==0.36.0; extra == "langchain-openai"
Requires-Dist: watchdog==6.0.0; sys_platform != "darwin" and extra == "langchain-openai"
Requires-Dist: yarl==1.20.1; extra == "langchain-openai"
Requires-Dist: zstandard==0.25.0; extra == "langchain-openai"
Provides-Extra: langfuse
Requires-Dist: aiofiles==24.1.0; extra == "langfuse"
Requires-Dist: aiohappyeyeballs==2.6.1; extra == "langfuse"
Requires-Dist: aiohttp==3.12.15; extra == "langfuse"
Requires-Dist: aiosignal==1.4.0; extra == "langfuse"
Requires-Dist: altair==5.5.0; extra == "langfuse"
Requires-Dist: annotated-types==0.7.0; extra == "langfuse"
Requires-Dist: anyio==4.10.0; extra == "langfuse"
Requires-Dist: attrs==25.3.0; extra == "langfuse"
Requires-Dist: azure-core==1.35.1; extra == "langfuse"
Requires-Dist: azure-identity==1.25.0; extra == "langfuse"
Requires-Dist: azure-storage-blob==12.26.0; extra == "langfuse"
Requires-Dist: backoff==2.2.1; extra == "langfuse"
Requires-Dist: blinker==1.9.0; extra == "langfuse"
Requires-Dist: boto3==1.40.35; extra == "langfuse"
Requires-Dist: botocore==1.40.35; extra == "langfuse"
Requires-Dist: cachetools==6.2.0; extra == "langfuse"
Requires-Dist: certifi==2025.8.3; extra == "langfuse"
Requires-Dist: cffi==2.0.0; platform_python_implementation != "PyPy" and extra == "langfuse"
Requires-Dist: charset-normalizer==3.4.3; extra == "langfuse"
Requires-Dist: click==8.3.0; extra == "langfuse"
Requires-Dist: colorama==0.4.6; sys_platform == "win32" and extra == "langfuse"
Requires-Dist: cryptography==46.0.1; extra == "langfuse"
Requires-Dist: distro==1.9.0; extra == "langfuse"
Requires-Dist: fastapi==0.117.1; extra == "langfuse"
Requires-Dist: frozenlist==1.7.0; extra == "langfuse"
Requires-Dist: gitdb==4.0.12; extra == "langfuse"
Requires-Dist: gitpython==3.1.45; extra == "langfuse"
Requires-Dist: googleapis-common-protos==1.70.0; extra == "langfuse"
Requires-Dist: h11==0.16.0; extra == "langfuse"
Requires-Dist: httpcore==1.0.9; extra == "langfuse"
Requires-Dist: httpx==0.28.1; extra == "langfuse"
Requires-Dist: idna==3.10; extra == "langfuse"
Requires-Dist: importlib-metadata==8.7.0; extra == "langfuse"
Requires-Dist: isodate==0.7.2; extra == "langfuse"
Requires-Dist: jinja2==3.1.6; extra == "langfuse"
Requires-Dist: jiter==0.11.0; extra == "langfuse"
Requires-Dist: jmespath==1.0.1; extra == "langfuse"
Requires-Dist: jsonschema-specifications==2025.9.1; extra == "langfuse"
Requires-Dist: jsonschema==4.25.1; extra == "langfuse"
Requires-Dist: langfuse==3.5.0; extra == "langfuse"
Requires-Dist: markdown-it-py==4.0.0; extra == "langfuse"
Requires-Dist: markupsafe==3.0.2; extra == "langfuse"
Requires-Dist: mdurl==0.1.2; extra == "langfuse"
Requires-Dist: msal-extensions==1.3.1; extra == "langfuse"
Requires-Dist: msal==1.33.0; extra == "langfuse"
Requires-Dist: multidict==6.6.4; extra == "langfuse"
Requires-Dist: narwhals==2.5.0; extra == "langfuse"
Requires-Dist: numpy==2.3.3; extra == "langfuse"
Requires-Dist: openai==1.108.1; extra == "langfuse"
Requires-Dist: opentelemetry-api==1.37.0; extra == "langfuse"
Requires-Dist: opentelemetry-exporter-otlp-proto-common==1.37.0; extra == "langfuse"
Requires-Dist: opentelemetry-exporter-otlp-proto-http==1.37.0; extra == "langfuse"
Requires-Dist: opentelemetry-proto==1.37.0; extra == "langfuse"
Requires-Dist: opentelemetry-sdk==1.37.0; extra == "langfuse"
Requires-Dist: opentelemetry-semantic-conventions==0.58b0; extra == "langfuse"
Requires-Dist: packaging==25.0; extra == "langfuse"
Requires-Dist: pandas==2.3.2; extra == "langfuse"
Requires-Dist: pillow==11.3.0; extra == "langfuse"
Requires-Dist: propcache==0.3.2; extra == "langfuse"
Requires-Dist: protobuf==6.32.1; extra == "langfuse"
Requires-Dist: pyarrow==21.0.0; extra == "langfuse"
Requires-Dist: pycparser==2.23; (implementation_name != "PyPy" and platform_python_implementation != "PyPy") and extra == "langfuse"
Requires-Dist: pydantic-core==2.33.2; extra == "langfuse"
Requires-Dist: pydantic==2.11.9; extra == "langfuse"
Requires-Dist: pydeck==0.9.1; extra == "langfuse"
Requires-Dist: pygments==2.19.2; extra == "langfuse"
Requires-Dist: pyjwt==2.10.1; extra == "langfuse"
Requires-Dist: python-dateutil==2.9.0.post0; extra == "langfuse"
Requires-Dist: python-json-logger==3.3.0; extra == "langfuse"
Requires-Dist: pytz==2025.2; extra == "langfuse"
Requires-Dist: pyyaml==6.0.2; extra == "langfuse"
Requires-Dist: ragelo==0.1.6; extra == "langfuse"
Requires-Dist: referencing==0.36.2; extra == "langfuse"
Requires-Dist: requests==2.32.5; extra == "langfuse"
Requires-Dist: rich==14.1.0; extra == "langfuse"
Requires-Dist: rpds-py==0.27.1; extra == "langfuse"
Requires-Dist: s3transfer==0.14.0; extra == "langfuse"
Requires-Dist: shellingham==1.5.4; extra == "langfuse"
Requires-Dist: six==1.17.0; extra == "langfuse"
Requires-Dist: smmap==5.0.2; extra == "langfuse"
Requires-Dist: sniffio==1.3.1; extra == "langfuse"
Requires-Dist: sse-starlette==3.0.2; extra == "langfuse"
Requires-Dist: starlette==0.48.0; extra == "langfuse"
Requires-Dist: streamlit==1.49.1; extra == "langfuse"
Requires-Dist: tabulate==0.9.0; extra == "langfuse"
Requires-Dist: tenacity==9.1.2; extra == "langfuse"
Requires-Dist: toml==0.10.2; extra == "langfuse"
Requires-Dist: tornado==6.5.2; extra == "langfuse"
Requires-Dist: tqdm==4.67.1; extra == "langfuse"
Requires-Dist: typer==0.19.1; extra == "langfuse"
Requires-Dist: typing-extensions==4.15.0; extra == "langfuse"
Requires-Dist: typing-inspection==0.4.1; extra == "langfuse"
Requires-Dist: tzdata==2025.2; extra == "langfuse"
Requires-Dist: urllib3==2.5.0; extra == "langfuse"
Requires-Dist: uvicorn==0.36.0; extra == "langfuse"
Requires-Dist: watchdog==6.0.0; sys_platform != "darwin" and extra == "langfuse"
Requires-Dist: wrapt==1.17.3; extra == "langfuse"
Requires-Dist: yarl==1.20.1; extra == "langfuse"
Requires-Dist: zipp==3.23.0; extra == "langfuse"
Provides-Extra: mcp
Requires-Dist: aiofiles==24.1.0; extra == "mcp"
Requires-Dist: aiohappyeyeballs==2.6.1; extra == "mcp"
Requires-Dist: aiohttp==3.12.15; extra == "mcp"
Requires-Dist: aiosignal==1.4.0; extra == "mcp"
Requires-Dist: altair==5.5.0; extra == "mcp"
Requires-Dist: annotated-types==0.7.0; extra == "mcp"
Requires-Dist: anyio==4.10.0; extra == "mcp"
Requires-Dist: attrs==25.3.0; extra == "mcp"
Requires-Dist: azure-core==1.35.1; extra == "mcp"
Requires-Dist: azure-identity==1.25.0; extra == "mcp"
Requires-Dist: azure-storage-blob==12.26.0; extra == "mcp"
Requires-Dist: blinker==1.9.0; extra == "mcp"
Requires-Dist: boto3==1.40.35; extra == "mcp"
Requires-Dist: botocore==1.40.35; extra == "mcp"
Requires-Dist: cachetools==6.2.0; extra == "mcp"
Requires-Dist: certifi==2025.8.3; extra == "mcp"
Requires-Dist: cffi==2.0.0; platform_python_implementation != "PyPy" and extra == "mcp"
Requires-Dist: charset-normalizer==3.4.3; extra == "mcp"
Requires-Dist: click==8.3.0; extra == "mcp"
Requires-Dist: colorama==0.4.6; sys_platform == "win32" and extra == "mcp"
Requires-Dist: cryptography==46.0.1; extra == "mcp"
Requires-Dist: distro==1.9.0; extra == "mcp"
Requires-Dist: fastapi==0.117.1; extra == "mcp"
Requires-Dist: frozenlist==1.7.0; extra == "mcp"
Requires-Dist: gitdb==4.0.12; extra == "mcp"
Requires-Dist: gitpython==3.1.45; extra == "mcp"
Requires-Dist: h11==0.16.0; extra == "mcp"
Requires-Dist: httpcore==1.0.9; extra == "mcp"
Requires-Dist: httpx-sse==0.4.1; python_full_version >= "3.13" and extra == "mcp"
Requires-Dist: httpx==0.28.1; extra == "mcp"
Requires-Dist: idna==3.10; extra == "mcp"
Requires-Dist: isodate==0.7.2; extra == "mcp"
Requires-Dist: jinja2==3.1.6; extra == "mcp"
Requires-Dist: jiter==0.11.0; extra == "mcp"
Requires-Dist: jmespath==1.0.1; extra == "mcp"
Requires-Dist: jsonschema-specifications==2025.9.1; extra == "mcp"
Requires-Dist: jsonschema==4.25.1; extra == "mcp"
Requires-Dist: markdown-it-py==4.0.0; extra == "mcp"
Requires-Dist: markupsafe==3.0.2; extra == "mcp"
Requires-Dist: mcp==1.14.1; python_full_version >= "3.13" and extra == "mcp"
Requires-Dist: mdurl==0.1.2; extra == "mcp"
Requires-Dist: msal-extensions==1.3.1; extra == "mcp"
Requires-Dist: msal==1.33.0; extra == "mcp"
Requires-Dist: multidict==6.6.4; extra == "mcp"
Requires-Dist: narwhals==2.5.0; extra == "mcp"
Requires-Dist: numpy==2.3.3; extra == "mcp"
Requires-Dist: openai==1.108.1; extra == "mcp"
Requires-Dist: packaging==25.0; extra == "mcp"
Requires-Dist: pandas==2.3.2; extra == "mcp"
Requires-Dist: pillow==11.3.0; extra == "mcp"
Requires-Dist: propcache==0.3.2; extra == "mcp"
Requires-Dist: protobuf==6.32.1; extra == "mcp"
Requires-Dist: pyarrow==21.0.0; extra == "mcp"
Requires-Dist: pycparser==2.23; (implementation_name != "PyPy" and platform_python_implementation != "PyPy") and extra == "mcp"
Requires-Dist: pydantic-core==2.33.2; extra == "mcp"
Requires-Dist: pydantic-settings==2.10.1; python_full_version >= "3.13" and extra == "mcp"
Requires-Dist: pydantic==2.11.9; extra == "mcp"
Requires-Dist: pydeck==0.9.1; extra == "mcp"
Requires-Dist: pygments==2.19.2; extra == "mcp"
Requires-Dist: pyjwt==2.10.1; extra == "mcp"
Requires-Dist: python-dateutil==2.9.0.post0; extra == "mcp"
Requires-Dist: python-dotenv==1.1.1; python_full_version >= "3.13" and extra == "mcp"
Requires-Dist: python-json-logger==3.3.0; extra == "mcp"
Requires-Dist: python-multipart==0.0.20; python_full_version >= "3.13" and extra == "mcp"
Requires-Dist: pytz==2025.2; extra == "mcp"
Requires-Dist: pywin32==311; (python_full_version >= "3.13" and sys_platform == "win32") and extra == "mcp"
Requires-Dist: pyyaml==6.0.2; extra == "mcp"
Requires-Dist: ragelo==0.1.6; extra == "mcp"
Requires-Dist: referencing==0.36.2; extra == "mcp"
Requires-Dist: requests==2.32.5; extra == "mcp"
Requires-Dist: rich==14.1.0; extra == "mcp"
Requires-Dist: rpds-py==0.27.1; extra == "mcp"
Requires-Dist: s3transfer==0.14.0; extra == "mcp"
Requires-Dist: shellingham==1.5.4; extra == "mcp"
Requires-Dist: six==1.17.0; extra == "mcp"
Requires-Dist: smmap==5.0.2; extra == "mcp"
Requires-Dist: sniffio==1.3.1; extra == "mcp"
Requires-Dist: sse-starlette==3.0.2; extra == "mcp"
Requires-Dist: starlette==0.48.0; extra == "mcp"
Requires-Dist: streamlit==1.49.1; extra == "mcp"
Requires-Dist: tabulate==0.9.0; extra == "mcp"
Requires-Dist: tenacity==9.1.2; extra == "mcp"
Requires-Dist: toml==0.10.2; extra == "mcp"
Requires-Dist: tornado==6.5.2; extra == "mcp"
Requires-Dist: tqdm==4.67.1; extra == "mcp"
Requires-Dist: typer==0.19.1; extra == "mcp"
Requires-Dist: typing-extensions==4.15.0; extra == "mcp"
Requires-Dist: typing-inspection==0.4.1; extra == "mcp"
Requires-Dist: tzdata==2025.2; extra == "mcp"
Requires-Dist: urllib3==2.5.0; extra == "mcp"
Requires-Dist: uvicorn==0.36.0; extra == "mcp"
Requires-Dist: watchdog==6.0.0; sys_platform != "darwin" and extra == "mcp"
Requires-Dist: yarl==1.20.1; extra == "mcp"
Provides-Extra: openai
Requires-Dist: aiofiles==24.1.0; extra == "openai"
Requires-Dist: aiohappyeyeballs==2.6.1; extra == "openai"
Requires-Dist: aiohttp==3.12.15; extra == "openai"
Requires-Dist: aiosignal==1.4.0; extra == "openai"
Requires-Dist: altair==5.5.0; extra == "openai"
Requires-Dist: annotated-types==0.7.0; extra == "openai"
Requires-Dist: anyio==4.10.0; extra == "openai"
Requires-Dist: attrs==25.3.0; extra == "openai"
Requires-Dist: azure-core==1.35.1; extra == "openai"
Requires-Dist: azure-identity==1.25.0; extra == "openai"
Requires-Dist: azure-storage-blob==12.26.0; extra == "openai"
Requires-Dist: blinker==1.9.0; extra == "openai"
Requires-Dist: boto3==1.40.35; extra == "openai"
Requires-Dist: botocore==1.40.35; extra == "openai"
Requires-Dist: cachetools==6.2.0; extra == "openai"
Requires-Dist: certifi==2025.8.3; extra == "openai"
Requires-Dist: cffi==2.0.0; platform_python_implementation != "PyPy" and extra == "openai"
Requires-Dist: charset-normalizer==3.4.3; extra == "openai"
Requires-Dist: click==8.3.0; extra == "openai"
Requires-Dist: colorama==0.4.6; sys_platform == "win32" and extra == "openai"
Requires-Dist: cryptography==46.0.1; extra == "openai"
Requires-Dist: distro==1.9.0; extra == "openai"
Requires-Dist: fastapi==0.117.1; extra == "openai"
Requires-Dist: frozenlist==1.7.0; extra == "openai"
Requires-Dist: gitdb==4.0.12; extra == "openai"
Requires-Dist: gitpython==3.1.45; extra == "openai"
Requires-Dist: h11==0.16.0; extra == "openai"
Requires-Dist: httpcore==1.0.9; extra == "openai"
Requires-Dist: httpx==0.28.1; extra == "openai"
Requires-Dist: idna==3.10; extra == "openai"
Requires-Dist: isodate==0.7.2; extra == "openai"
Requires-Dist: jinja2==3.1.6; extra == "openai"
Requires-Dist: jiter==0.11.0; extra == "openai"
Requires-Dist: jmespath==1.0.1; extra == "openai"
Requires-Dist: jsonschema-specifications==2025.9.1; extra == "openai"
Requires-Dist: jsonschema==4.25.1; extra == "openai"
Requires-Dist: markdown-it-py==4.0.0; extra == "openai"
Requires-Dist: markupsafe==3.0.2; extra == "openai"
Requires-Dist: mdurl==0.1.2; extra == "openai"
Requires-Dist: msal-extensions==1.3.1; extra == "openai"
Requires-Dist: msal==1.33.0; extra == "openai"
Requires-Dist: multidict==6.6.4; extra == "openai"
Requires-Dist: narwhals==2.5.0; extra == "openai"
Requires-Dist: numpy==2.3.3; extra == "openai"
Requires-Dist: openai==1.108.1; extra == "openai"
Requires-Dist: packaging==25.0; extra == "openai"
Requires-Dist: pandas==2.3.2; extra == "openai"
Requires-Dist: pillow==11.3.0; extra == "openai"
Requires-Dist: propcache==0.3.2; extra == "openai"
Requires-Dist: protobuf==6.32.1; extra == "openai"
Requires-Dist: pyarrow==21.0.0; extra == "openai"
Requires-Dist: pycparser==2.23; (implementation_name != "PyPy" and platform_python_implementation != "PyPy") and extra == "openai"
Requires-Dist: pydantic-core==2.33.2; extra == "openai"
Requires-Dist: pydantic==2.11.9; extra == "openai"
Requires-Dist: pydeck==0.9.1; extra == "openai"
Requires-Dist: pygments==2.19.2; extra == "openai"
Requires-Dist: pyjwt==2.10.1; extra == "openai"
Requires-Dist: python-dateutil==2.9.0.post0; extra == "openai"
Requires-Dist: python-json-logger==3.3.0; extra == "openai"
Requires-Dist: pytz==2025.2; extra == "openai"
Requires-Dist: pyyaml==6.0.2; extra == "openai"
Requires-Dist: ragelo==0.1.6; extra == "openai"
Requires-Dist: referencing==0.36.2; extra == "openai"
Requires-Dist: requests==2.32.5; extra == "openai"
Requires-Dist: rich==14.1.0; extra == "openai"
Requires-Dist: rpds-py==0.27.1; extra == "openai"
Requires-Dist: s3transfer==0.14.0; extra == "openai"
Requires-Dist: shellingham==1.5.4; extra == "openai"
Requires-Dist: six==1.17.0; extra == "openai"
Requires-Dist: smmap==5.0.2; extra == "openai"
Requires-Dist: sniffio==1.3.1; extra == "openai"
Requires-Dist: sse-starlette==3.0.2; extra == "openai"
Requires-Dist: starlette==0.48.0; extra == "openai"
Requires-Dist: streamlit==1.49.1; extra == "openai"
Requires-Dist: tabulate==0.9.0; extra == "openai"
Requires-Dist: tenacity==9.1.2; extra == "openai"
Requires-Dist: toml==0.10.2; extra == "openai"
Requires-Dist: tornado==6.5.2; extra == "openai"
Requires-Dist: tqdm==4.67.1; extra == "openai"
Requires-Dist: typer==0.19.1; extra == "openai"
Requires-Dist: typing-extensions==4.15.0; extra == "openai"
Requires-Dist: typing-inspection==0.4.1; extra == "openai"
Requires-Dist: tzdata==2025.2; extra == "openai"
Requires-Dist: urllib3==2.5.0; extra == "openai"
Requires-Dist: uvicorn==0.36.0; extra == "openai"
Requires-Dist: watchdog==6.0.0; sys_platform != "darwin" and extra == "openai"
Requires-Dist: yarl==1.20.1; extra == "openai"
Provides-Extra: all
Requires-Dist: aiofiles==24.1.0; extra == "all"
Requires-Dist: aiohappyeyeballs==2.6.1; extra == "all"
Requires-Dist: aiohttp==3.12.15; extra == "all"
Requires-Dist: aiosignal==1.4.0; extra == "all"
Requires-Dist: altair==5.5.0; extra == "all"
Requires-Dist: annotated-types==0.7.0; extra == "all"
Requires-Dist: anthropic==0.68.0; extra == "all"
Requires-Dist: anyio==4.10.0; extra == "all"
Requires-Dist: attrs==25.3.0; extra == "all"
Requires-Dist: azure-core==1.35.1; extra == "all"
Requires-Dist: azure-identity==1.25.0; extra == "all"
Requires-Dist: azure-storage-blob==12.26.0; extra == "all"
Requires-Dist: backoff==2.2.1; extra == "all"
Requires-Dist: blinker==1.9.0; extra == "all"
Requires-Dist: boto3==1.40.35; extra == "all"
Requires-Dist: botocore==1.40.35; extra == "all"
Requires-Dist: cachetools==6.2.0; extra == "all"
Requires-Dist: certifi==2025.8.3; extra == "all"
Requires-Dist: cffi==2.0.0; platform_python_implementation != "PyPy" and extra == "all"
Requires-Dist: charset-normalizer==3.4.3; extra == "all"
Requires-Dist: click==8.3.0; extra == "all"
Requires-Dist: colorama==0.4.6; sys_platform == "win32" and extra == "all"
Requires-Dist: cryptography==46.0.1; extra == "all"
Requires-Dist: distro==1.9.0; extra == "all"
Requires-Dist: docstring-parser==0.17.0; extra == "all"
Requires-Dist: fastapi==0.117.1; extra == "all"
Requires-Dist: frozenlist==1.7.0; extra == "all"
Requires-Dist: gitdb==4.0.12; extra == "all"
Requires-Dist: gitpython==3.1.45; extra == "all"
Requires-Dist: googleapis-common-protos==1.70.0; extra == "all"
Requires-Dist: greenlet==3.2.4; ((python_full_version < "3.14" and platform_machine == "AMD64") or (python_full_version < "3.14" and platform_machine == "WIN32") or (python_full_version < "3.14" and platform_machine == "aarch64") or (python_full_version < "3.14" and platform_machine == "amd64") or (python_full_version < "3.14" and platform_machine == "ppc64le") or (python_full_version < "3.14" and platform_machine == "win32") or (python_full_version < "3.14" and platform_machine == "x86_64")) an
Requires-Dist: h11==0.16.0; extra == "all"
Requires-Dist: httpcore==1.0.9; extra == "all"
Requires-Dist: httpx-sse==0.4.1; python_full_version >= "3.13" and extra == "all"
Requires-Dist: httpx==0.28.1; extra == "all"
Requires-Dist: idna==3.10; extra == "all"
Requires-Dist: importlib-metadata==8.7.0; extra == "all"
Requires-Dist: isodate==0.7.2; extra == "all"
Requires-Dist: jinja2==3.1.6; extra == "all"
Requires-Dist: jiter==0.11.0; extra == "all"
Requires-Dist: jmespath==1.0.1; extra == "all"
Requires-Dist: jsonpatch==1.33; extra == "all"
Requires-Dist: jsonpointer==3.0.0; extra == "all"
Requires-Dist: jsonschema-specifications==2025.9.1; extra == "all"
Requires-Dist: jsonschema==4.25.1; extra == "all"
Requires-Dist: langchain-anthropic==0.3.20; extra == "all"
Requires-Dist: langchain-aws==0.2.33; extra == "all"
Requires-Dist: langchain-core==0.3.76; extra == "all"
Requires-Dist: langchain-openai==0.3.33; extra == "all"
Requires-Dist: langchain-text-splitters==0.3.11; extra == "all"
Requires-Dist: langchain==0.3.27; extra == "all"
Requires-Dist: langfuse==3.5.0; extra == "all"
Requires-Dist: langsmith==0.4.29; extra == "all"
Requires-Dist: markdown-it-py==4.0.0; extra == "all"
Requires-Dist: markupsafe==3.0.2; extra == "all"
Requires-Dist: mcp==1.14.1; python_full_version >= "3.13" and extra == "all"
Requires-Dist: mdurl==0.1.2; extra == "all"
Requires-Dist: msal-extensions==1.3.1; extra == "all"
Requires-Dist: msal==1.33.0; extra == "all"
Requires-Dist: multidict==6.6.4; extra == "all"
Requires-Dist: narwhals==2.5.0; extra == "all"
Requires-Dist: numpy==2.3.3; extra == "all"
Requires-Dist: openai==1.108.1; extra == "all"
Requires-Dist: opentelemetry-api==1.37.0; extra == "all"
Requires-Dist: opentelemetry-exporter-otlp-proto-common==1.37.0; extra == "all"
Requires-Dist: opentelemetry-exporter-otlp-proto-http==1.37.0; extra == "all"
Requires-Dist: opentelemetry-proto==1.37.0; extra == "all"
Requires-Dist: opentelemetry-sdk==1.37.0; extra == "all"
Requires-Dist: opentelemetry-semantic-conventions==0.58b0; extra == "all"
Requires-Dist: orjson==3.11.3; platform_python_implementation != "PyPy" and extra == "all"
Requires-Dist: packaging==25.0; extra == "all"
Requires-Dist: pandas==2.3.2; extra == "all"
Requires-Dist: pillow==11.3.0; extra == "all"
Requires-Dist: propcache==0.3.2; extra == "all"
Requires-Dist: protobuf==6.32.1; extra == "all"
Requires-Dist: pyarrow==21.0.0; extra == "all"
Requires-Dist: pycparser==2.23; (implementation_name != "PyPy" and platform_python_implementation != "PyPy") and extra == "all"
Requires-Dist: pydantic-core==2.33.2; extra == "all"
Requires-Dist: pydantic-settings==2.10.1; python_full_version >= "3.13" and extra == "all"
Requires-Dist: pydantic==2.11.9; extra == "all"
Requires-Dist: pydeck==0.9.1; extra == "all"
Requires-Dist: pygments==2.19.2; extra == "all"
Requires-Dist: pyjwt==2.10.1; extra == "all"
Requires-Dist: python-dateutil==2.9.0.post0; extra == "all"
Requires-Dist: python-dotenv==1.1.1; python_full_version >= "3.13" and extra == "all"
Requires-Dist: python-json-logger==3.3.0; extra == "all"
Requires-Dist: python-multipart==0.0.20; python_full_version >= "3.13" and extra == "all"
Requires-Dist: pytz==2025.2; extra == "all"
Requires-Dist: pywin32==311; (python_full_version >= "3.13" and sys_platform == "win32") and extra == "all"
Requires-Dist: pyyaml==6.0.2; extra == "all"
Requires-Dist: ragelo==0.1.6; extra == "all"
Requires-Dist: referencing==0.36.2; extra == "all"
Requires-Dist: regex==2025.9.18; extra == "all"
Requires-Dist: requests-toolbelt==1.0.0; extra == "all"
Requires-Dist: requests==2.32.5; extra == "all"
Requires-Dist: rich==14.1.0; extra == "all"
Requires-Dist: rpds-py==0.27.1; extra == "all"
Requires-Dist: s3transfer==0.14.0; extra == "all"
Requires-Dist: shellingham==1.5.4; extra == "all"
Requires-Dist: six==1.17.0; extra == "all"
Requires-Dist: smmap==5.0.2; extra == "all"
Requires-Dist: sniffio==1.3.1; extra == "all"
Requires-Dist: sqlalchemy==2.0.43; extra == "all"
Requires-Dist: sse-starlette==3.0.2; extra == "all"
Requires-Dist: starlette==0.48.0; extra == "all"
Requires-Dist: streamlit==1.49.1; extra == "all"
Requires-Dist: tabulate==0.9.0; extra == "all"
Requires-Dist: tenacity==9.1.2; extra == "all"
Requires-Dist: tiktoken==0.11.0; extra == "all"
Requires-Dist: toml==0.10.2; extra == "all"
Requires-Dist: tornado==6.5.2; extra == "all"
Requires-Dist: tqdm==4.67.1; extra == "all"
Requires-Dist: typer==0.19.1; extra == "all"
Requires-Dist: typing-extensions==4.15.0; extra == "all"
Requires-Dist: typing-inspection==0.4.1; extra == "all"
Requires-Dist: tzdata==2025.2; extra == "all"
Requires-Dist: urllib3==2.5.0; extra == "all"
Requires-Dist: uvicorn==0.36.0; extra == "all"
Requires-Dist: watchdog==6.0.0; sys_platform != "darwin" and extra == "all"
Requires-Dist: wrapt==1.17.3; extra == "all"
Requires-Dist: yarl==1.20.1; extra == "all"
Requires-Dist: zipp==3.23.0; extra == "all"
Requires-Dist: zstandard==0.25.0; extra == "all"
